brightpath/__init__.py
brightpath/bwconverter.py
brightpath/simaproconverter.py
brightpath/utils.py
brightpath/data/export/correspondence_biosphere_flows.yaml
brightpath/data/export/ecoinvent_to_uvek_mapping.csv
brightpath/data/export/ei_transport.csv
brightpath/data/export/flows_biosphere_39.csv
brightpath/data/export/simapro-biosphere.json
brightpath/data/export/simapro-technosphere-3.5.csv
brightpath/data/export/simapro_blacklist.yaml
brightpath/data/export/simapro_ei_exceptions.yaml
brightpath/data/export/simapro_fields.yaml
brightpath/data/export/simapro_headers.yaml
brightpath/data/export/simapro_subcompartments.yaml
brightpath/data/export/simapro_units.yaml
brightpath/data/export/uvek_blacklist.yaml
brightpath/data/export/uvek_conversion_factors.yaml
brightpath/data/export/waste_exchange_names.yaml
brightpath-0.0.1.dist-info/licenses/LICENSE
brightpath-0.0.1.dist-info/METADATA
brightpath-0.0.1.dist-info/WHEEL
brightpath-0.0.1.dist-info/top_level.txt
brightpath-0.0.1.dist-info/RECORD
