Metadata-Version: 2.4
Name: brightpath
Version: 0.0.1
Summary: Convert Brightway2 LCI data to Simapro and back.
Author-email: Romain Sacchi <romain.sacchi@psi.ch>
License: BSD 3-Clause License
Project-URL: Homepage, https://github.com/polca/brightpath
Classifier: Intended Audience :: End Users/Desktop
Classifier: Intended Audience :: Developers
Classifier: Intended Audience :: Science/Research
Classifier: License :: OSI Approved :: BSD License
Classifier: Operating System :: MacOS :: MacOS X
Classifier: Operating System :: Microsoft :: Windows
Classifier: Operating System :: POSIX
Classifier: Programming Language :: Python
Classifier: Programming Language :: Python :: 3
Classifier: Programming Language :: Python :: 3.9
Classifier: Topic :: Scientific/Engineering :: Information Analysis
Classifier: Topic :: Scientific/Engineering :: Mathematics
Classifier: Topic :: Scientific/Engineering :: Visualization
Requires-Python: >=3.9
License-File: LICENSE
Requires-Dist: bw2io
Requires-Dist: prettytable>=3
Requires-Dist: PyYAML>=6
Dynamic: license-file
